ConvTool/ConvTool.py
ConvTool/__init__.py
ConvTool-1.0.dist-info/LICENSE
ConvTool-1.0.dist-info/METADATA
ConvTool-1.0.dist-info/WHEEL
ConvTool-1.0.dist-info/top_level.txt
ConvTool-1.0.dist-info/RECORD
