Metadata-Version: 2.1
Name: ConvTool
Version: 1.0
Summary: A unified package to convert your videos or images to another image/video format. Convert a whole folder from that format to a different one, or if you prefer, convert just one! 🥵
Home-page: https://github.com/ElHaban3ro/ConvTool
Author: ElHaban3ro
Author-email: habanferd@gmail.com
License: MIT
Keywords: python converter video-processing video-converter image-processing image-converter
Classifier: Programming Language :: Python :: 3.10
License-File: LICENSE
Requires-Dist: moviepy (==1.0.3)
Requires-Dist: Pillow (==9.2.0)
